llm_unified_orchestrator/example.py
llm_unified_orchestrator/core/task.py
llm_unified_orchestrator/core/workflow.py
llm_unified_orchestrator/core/prompts/base.py
llm_unified_orchestrator/data_store/repository.py
llm_unified_orchestrator/executors/generic_executor.py
llm_unified_orchestrator/executors/task_finalizer.py
llm_unified_orchestrator/factories/prompt_provider_factory.py
llm_unified_orchestrator/factories/task_finalizer_factory.py
llm_unified_orchestrator/inference_api/__init__.py
llm_unified_orchestrator/inference_api/llm_config.py
llm_unified_orchestrator/inference_api/strategies/base.py
llm_unified_orchestrator/inference_api/strategies/google_ai_studio.py
llm_unified_orchestrator/inference_api/strategies/gpt_oss.py
llm_unified_orchestrator/inference_api/strategies/ollama.py
llm_unified_orchestrator/inference_api/strategies/ollama_slim.py
llm_unified_orchestrator/inference_api/strategies/openai.py
llm_unified_orchestrator/inference_api/strategies/strategy_factory.py
llm_unified_orchestrator/mlflow/mlflow_config.py
llm_unified_orchestrator/mlflow/prompts/prompt_provider.py
llm_unified_orchestrator-1.0.3.dist-info/licenses/LICENSE
llm_unified_orchestrator-1.0.3.dist-info/METADATA
llm_unified_orchestrator-1.0.3.dist-info/WHEEL
llm_unified_orchestrator-1.0.3.dist-info/top_level.txt
llm_unified_orchestrator-1.0.3.dist-info/RECORD
